MANIFEST.in
README.rst
setup.py
cy_Oracle/__init__.py
cy_Oracle/cyOracle.py
cy_Oracle.egg-info/PKG-INFO
cy_Oracle.egg-info/SOURCES.txt
cy_Oracle.egg-info/dependency_links.txt
cy_Oracle.egg-info/not-zip-safe
cy_Oracle.egg-info/requires.txt
cy_Oracle.egg-info/top_level.txt
sample/example_1.py
sample/example_2.py
sample/example_3.py