Metadata-Version: 1.0
Name: cy-Oracle
Version: 0.3.1
Summary: Extension to cx_Oracle to handle Oracle object types
Home-page: UNKNOWN
Author: Nuuk Zweiundvierzig
Author-email: nuuk42@yahoo.com
License: MIT
Platform: UNKNOWN
